ondewo_bpi/__init__.py
ondewo_bpi/bpi_server.py
ondewo_bpi/bpi_services.py
ondewo_bpi/config.py
ondewo_bpi/conftest.py
ondewo_bpi/constants.py
ondewo_bpi/helpers.py
ondewo_bpi/intent_max_trigger_handler.py
ondewo_bpi/message_handler.py
ondewo_bpi/test_message_handler.py
ondewo_bpi_qa/__init__.py
ondewo_bpi_qa/bpi_qa_base_server.py
ondewo_bpi_qa/bpi_qa_server.py
ondewo_bpi_qa/bpi_qa_services.py
ondewo_bpi_qa/config.py
ondewo_bpi_qa/constants.py
ondewo_bpi_qa/helper.py
ondewo_bpi-4.1.1.dist-info/LICENSE
ondewo_bpi-4.1.1.dist-info/LICENSE.md
ondewo_bpi-4.1.1.dist-info/METADATA
ondewo_bpi-4.1.1.dist-info/WHEEL
ondewo_bpi-4.1.1.dist-info/top_level.txt
ondewo_bpi-4.1.1.dist-info/RECORD
