Metadata-Version: 2.1
Name: ondewo-bpi
Version: 4.1.1
Summary: This library starts a proxy for the cai server allowing for fulfillment hooks.
Home-page: https://bitbucket.org/ondewo/ondewo-bpi
Author: Ondewo GbmH
Author-email: info@ondewo.com
License: UNKNOWN
Platform: UNKNOWN
Classifier: Programming Language :: Python :: 3
Classifier: Operating System :: OS Independent
Classifier: Development Status :: 3 - Alpha
Classifier: Topic :: Software Development :: Libraries
Requires-Python: >=3.0.1
